spithon/__init__.py
spithon/cli.py
spithon/cmds/__init__.py
spithon/cmds/benchmark.py
spithon/cmds/common.py
spithon/cmds/gpio.py
spithon/cmds/spi.py
spithon/core/__init__.py
spithon/core/config.py
spithon/core/gpio.py
spithon/core/spi.py
spithon-0.1.0.dist-info/LICENSE
spithon-0.1.0.dist-info/METADATA
spithon-0.1.0.dist-info/WHEEL
spithon-0.1.0.dist-info/entry_points.txt
spithon-0.1.0.dist-info/top_level.txt
spithon-0.1.0.dist-info/RECORD
