Metadata-Version: 2.1
Name: spithon
Version: 0.1.0
Summary: A Raspberry Pi CLI tool for SPI and GPIO communication.
Home-page: https://github.com/fronzbot/spithon
Author: Kevin Fronczak
Author-email: kfronczak@gmail.com
License: A CLI for SPI/GPIO manipulation on a Raspberry Pi.
Platform: UNKNOWN
Classifier: License :: OSI Approved :: Apache Software License
Classifier: Programming Language :: Python :: 3.8
Classifier: Programming Language :: Python :: 3.9
Classifier: Programming Language :: Python :: 3.10
Classifier: Programming Language :: Python :: 3.11
License-File: LICENSE
Requires-Dist: cachetools (==5.3.1)
Requires-Dist: click (==8.1.3)
Requires-Dist: crc (==4.2.0)
Requires-Dist: spidev (==3.6) ; sys_platform == "linux"
Requires-Dist: RPi.GPIO (==0.7.1) ; sys_platform == "linux"
